README.rst
setup.py
motechjavasphinx/__init__.py
motechjavasphinx/motech.py
motechjavasphinx.egg-info/PKG-INFO
motechjavasphinx.egg-info/SOURCES.txt
motechjavasphinx.egg-info/dependency_links.txt
motechjavasphinx.egg-info/requires.txt
motechjavasphinx.egg-info/top_level.txt