Metadata-Version: 1.1
Name: motechjavasphinx
Version: 0.2
Summary: Sphinx extension for executing javasphinx to documenting Java projects
Home-page: http://github.com/motech/motechjavasphinx
Author: Grameen Foundation
Author-email: rlarubbio@grameenfoundation.org
License: UNKNOWN
Platform: UNKNOWN
Classifier: Programming Language :: Python
Classifier: Development Status :: 4 - Beta
Classifier: Operating System :: OS Independent
Classifier: License :: OSI Approved :: BSD License
Classifier: Intended Audience :: Developers
Classifier: Topic :: Software Development :: Libraries
